pyeventroute/__init__.py
pyeventroute/configs.py
pyeventroute/route.py
pyeventroute/static.py
pyeventroute-0.0.6.dist-info/LICENSE
pyeventroute-0.0.6.dist-info/METADATA
pyeventroute-0.0.6.dist-info/WHEEL
pyeventroute-0.0.6.dist-info/top_level.txt
pyeventroute-0.0.6.dist-info/RECORD
